hiukao/__init__.py
hiukao/message.py
hiukao-0.0.2.dist-info/METADATA
hiukao-0.0.2.dist-info/WHEEL
hiukao-0.0.2.dist-info/top_level.txt
hiukao-0.0.2.dist-info/RECORD
