Metadata-Version: 2.1
Name: hiukao
Version: 0.0.2
Summary: A message from HiuKao
Author: HiuKao
Author-email: <nguoidaulungsiucapvjppro@gmail.com>
Keywords: python
Classifier: Development Status :: 1 - Planning
Classifier: Intended Audience :: Developers
Classifier: Programming Language :: Python :: 3
Classifier: Operating System :: Unix
Classifier: Operating System :: MacOS :: MacOS X
Classifier: Operating System :: Microsoft :: Windows
